{
    "Alcanfores": [
        {"numero": "PRIMERA: ", "titulo": "ANTECEDENTES", "reemplazo": "P R I M E R A:"},
        {"numero": "SEGUNDA: ", "titulo": "BIENES OBJETO DEL CONTRATO", "reemplazo": "S E G U N D A:"},
        {"numero": "TERCERA: ", "titulo": "OBJETO DEL PRESENTE CONTRATO", "reemplazo": "T E R C E R A:"},
        {"numero": "CUARTA: ", "titulo": "RESERVA DE PROPIEDAD", "reemplazo": "C U A R T A:"},
        {"numero": "QUINTA: ", "titulo": "PRECIO Y FORMA DE PAGO", "reemplazo": "Q U I N T A:"},
        {"numero": "SEXTA: ", "titulo": "RESOLUCION DEL CONTRATO", "reemplazo": "S E X T A:"},
        {"numero": "SEPTIMA: ", "titulo": "LAVADO DE ACTIVOS", "reemplazo": "S E P T I M A:"},
        {"numero": "OCTAVA: ", "titulo": "EXISTENCIA", "reemplazo": "O C T A V A:"},
        {"numero": "NOVENA: ", "titulo": "ENTREGA DE LOS INMUEBLES", "reemplazo": "N O V E N A:"},
        {"numero": "DECIMA: ", "titulo": "EQUIVALENCIA DE LAS PRESTACIONES", "reemplazo": "D E C I M A:"},
        {"numero": "DECIMO PRIMERA: ", "titulo": "SITUACION DEL PROYECTO Y/O DE LOS INMUEBLES", "reemplazo": "DECIMO PRIMERA:"},
        {"numero": "DECIMO SEGUNDA: ", "titulo": "INDEPENDIZACION Y AUTORIZACION PARA GESTIONES", "reemplazo": "DECIMO SEGUNDA:"},
        {"numero": "DECIMO TERCERA: ", "titulo": "IMPUESTOS Y ARBITRIOS", "reemplazo": "DECIMO TERCERA:"},
        {"numero": "DECIMO CUARTA: ", "titulo": "DE LA ADMINISTRACION DEL EDIFICIO", "reemplazo": "DECIMO CUARTA:"},
        {"numero": "DECIMO QUINTA: ", "titulo": "GASTOS DE MANTENIMIENTO", "reemplazo": "DECIMO QUINTA:"},
        {"numero": "DECIMO SEXTA: ", "titulo": "GASTOS NOTARIALES Y REGISTRALES", "reemplazo": "DECIMO SEXTA:"},
        {"numero": "DECIMO SEPTIMA: ", "titulo": "DE LA GARANTIA DE LOS INMUEBLES", "reemplazo": "DECIMO SEPTIMA:"},
        {"numero": "DECIMO OCTAVA: ", "titulo": "ACUERDO GLOBAL Y UNICO", "reemplazo": "DECIMO OCTAVA:"},
        {"numero": "DECIMO NOVENA: ", "titulo": "NOTIFICACIONES", "reemplazo": "DECIMO NOVENA:"},
        {"numero": "VIGESIMA: ", "titulo": "SOLUCION DE CONFLICTOS", "reemplazo": "V I G E S I M A:"}
    ],
    "Quatro Beta": [
        {"numero": "PRIMERA: ", "titulo": "ANTECEDENTES", "reemplazo": "P R I M E R A:"},
        {"numero": "SEGUNDA: ", "titulo": "BIENES OBJETO DEL CONTRATO", "reemplazo": "S E G U N D A:"},
        {"numero": "TERCERA: ", "titulo": "OBJETO DEL PRESENTE CONTRATO", "reemplazo": "T E R C E R A:"},
        {"numero": "CUARTA: ", "titulo": "RESERVA DE PROPIEDAD", "reemplazo": "C U A R T A:"},
        {"numero": "QUINTA: ", "titulo": "PRECIO Y FORMA DE PAGO", "reemplazo": "Q U I N T A:"},
        {"numero": "SEXTA: ", "titulo": "RESOLUCION DEL CONTRATO", "reemplazo": "S E X T A:"},
        {"numero": "SEPTIMA: ", "titulo": "LAVADO DE ACTIVOS", "reemplazo": "S E P T I M A:"},
        {"numero": "OCTAVA: ", "titulo": "EXISTENCIA", "reemplazo": "O C T A V A:"},
        {"numero": "NOVENA: ", "titulo": "ENTREGA DE LOS INMUEBLES", "reemplazo": "N O V E N A:"},
        {"numero": "DECIMA: ", "titulo": "EQUIVALENCIA DE LAS PRESTACIONES", "reemplazo": "D E C I M A:"},
        {"numero": "DECIMO PRIMERA: ", "titulo": "SITUACION DEL PROYECTO Y/O DE LOS INMUEBLES", "reemplazo": "DECIMO PRIMERA:"},
        {"numero": "DECIMO SEGUNDA: ", "titulo": "INDEPENDIZACION Y AUTORIZACION PARA GESTIONES", "reemplazo": "DECIMO SEGUNDA:"},
        {"numero": "DECIMO TERCERA: ", "titulo": "IMPUESTOS Y ARBITRIOS", "reemplazo": "DECIMO TERCERA:"},
        {"numero": "DECIMO CUARTA: ", "titulo": "DE LA ADMINISTRACION DEL EDIFICIO", "reemplazo": "DECIMO CUARTA:"},
        {"numero": "DECIMO QUINTA: ", "titulo": "GASTOS DE MANTENIMIENTO", "reemplazo": "DECIMO QUINTA:"},
        {"numero": "DECIMO SEXTA: ", "titulo": "GASTOS NOTARIALES Y REGISTRALES", "reemplazo": "DECIMO SEXTA:"},
        {"numero": "DECIMO SEPTIMA: ", "titulo": "DE LA GARANTIA DE LOS INMUEBLES", "reemplazo": "DECIMO SEPTIMA:"},
        {"numero": "DECIMO OCTAVA: ", "titulo": "ACUERDO GLOBAL Y UNICO", "reemplazo": "DECIMO OCTAVA:"},
        {"numero": "DECIMO NOVENA: ", "titulo": "NOTIFICACIONES", "reemplazo": "DECIMO NOVENA:"},
        {"numero": "VIGESIMA: ", "titulo": "SOLUCION DE CONFLICTOS", "reemplazo": "V I G E S I M A:"}
    ],
    "Quatro Epsilon": [
        {"numero": "PRIMERA: ", "titulo": "ANTECEDENTES", "reemplazo": "P R I M E R A:"},
        {"numero": "SEGUNDA: ", "titulo": "BIENES OBJETO DEL CONTRATO", "reemplazo": "S E G U N D A:"},
        {"numero": "TERCERA: ", "titulo": "OBJETO DEL PRESENTE CONTRATO", "reemplazo": "T E R C E R A:"},
        {"numero": "CUARTA: ", "titulo": "RESERVA DE PROPIEDAD", "reemplazo": "C U A R T A:"},
        {"numero": "QUINTA: ", "titulo": "PRECIO Y FORMA DE PAGO", "reemplazo": "Q U I N T A:"},
        {"numero": "SEXTA: ", "titulo": "RESOLUCION DEL CONTRATO", "reemplazo": "S E X T A:"},
        {"numero": "SEPTIMA: ", "titulo": "LAVADO DE ACTIVOS", "reemplazo": "S E P T I M A:"},
        {"numero": "OCTAVA: ", "titulo": "EXISTENCIA", "reemplazo": "O C T A V A:"},
        {"numero": "NOVENA: ", "titulo": "ENTREGA DE LOS INMUEBLES", "reemplazo": "N O V E N A:"},
        {"numero": "DECIMA: ", "titulo": "EQUIVALENCIA DE LAS PRESTACIONES", "reemplazo": "D E C I M A:"},
        {"numero": "DECIMO PRIMERA: ", "titulo": "SITUACION DEL PROYECTO Y/O DE LOS INMUEBLES", "reemplazo": "DECIMO PRIMERA:"},
        {"numero": "DECIMO SEGUNDA: ", "titulo": "INDEPENDIZACION Y AUTORIZACION PARA GESTIONES", "reemplazo": "DECIMO SEGUNDA:"},
        {"numero": "DECIMO TERCERA: ", "titulo": "IMPUESTOS Y ARBITRIOS", "reemplazo": "DECIMO TERCERA:"},
        {"numero": "DECIMO CUARTA: ", "titulo": "DE LA ADMINISTRACION DEL EDIFICIO", "reemplazo": "DECIMO CUARTA:"},
        {"numero": "DECIMO QUINTA: ", "titulo": "GASTOS DE MANTENIMIENTO", "reemplazo": "DECIMO QUINTA:"},
        {"numero": "DECIMO SEXTA: ", "titulo": "GASTOS NOTARIALES Y REGISTRALES", "reemplazo": "DECIMO SEXTA:"},
        {"numero": "DECIMO SEPTIMA: ", "titulo": "DE LA GARANTIA DE LOS INMUEBLES", "reemplazo": "DECIMO SEPTIMA:"},
        {"numero": "DECIMO OCTAVA: ", "titulo": "ACUERDO GLOBAL Y UNICO", "reemplazo": "DECIMO OCTAVA:"},
        {"numero": "DECIMO NOVENA: ", "titulo": "NOTIFICACIONES", "reemplazo": "DECIMO NOVENA:"},
        {"numero": "VIGESIMA: ", "titulo": "SOLUCION DE CONFLICTOS", "reemplazo": "V I G E S I M A:"}
    ],
    "CP Building SAC": [
        {"numero": "PRIMERA: ", "titulo": "ANTECEDENTES", "reemplazo": "P R I M E R A:"},
        {"numero": "SEGUNDA: ", "titulo": "OBJETO DEL CONTRATO", "reemplazo": "S E G U N D A:"},
        {"numero": "TERCERA: ", "titulo": "PRECIO DE VENTA", "reemplazo": "T E R C E R A:"},
        {"numero": "CUARTA: ", "titulo": "FORMA DE PAGO", "reemplazo": "C U A R T A:"},
        {"numero": "QUINTA: ", "titulo": "FIRMA DE LA ESCRITURA PUBLICA", "reemplazo": "Q U I N T A:"},
        {"numero": "SEXTA: ", "titulo": "GRAVAMENES", "reemplazo": "S E X T A:"},
        {"numero": "SETIMA: ", "titulo": "EQUIVALENCIA DE VALORES", "reemplazo": "S E T I M A:"},
        {"numero": "OCTAVA: ", "titulo": "ENTREGA DE LOS INMUEBLES", "reemplazo": "O C T A V A:"},
        {"numero": "NOVENA: ", "titulo": "OBLIGACIONES DE SANEAMIENTO", "reemplazo": "N O V E N A:"},
        {"numero": "DECIMA: ", "titulo": "MEMORIA DESCRIPTIVA DE ACABADOS Y PLANOS", "reemplazo": "D E C I M A:"},
        {"numero": "DECIMA PRIMERA: ", "titulo": "DECLARATORIA DE FABRICA E INDEPENDIZACION", "reemplazo": "DECIMA PRIMERA:"},
        {"numero": "DECIMA SEGUNDA: ", "titulo": "IMPUESTOS DE LEY", "reemplazo": "DECIMA SEGUNDA:"},
        {"numero": "DECIMA TERCERA: ", "titulo": "CLAUSULA RESOLUTORIA", "reemplazo": "DECIMA TERCERA:"},
        {"numero": "DECIMA CUARTA: ", "titulo": "TRABAJOS ADICIONALES EN LOS INMUEBLES", "reemplazo": "DECIMA CUARTA:"},
        {"numero": "DECIMA QUINTA: ", "titulo": "SITUACION LEGAL DEL INMUEBLE", "reemplazo": "DECIMA QUINTA:"},
        {"numero": "DECIMA SEXTA: ", "titulo": "ALCANCES DE LA COMPRA-VENTA", "reemplazo": "DECIMA SEXTA:"},
        {"numero": "DECIMA SEPTIMA: ", "titulo": "GASTOS NOTARIALES Y REGISTRALES", "reemplazo": "DECIMA SEPTIMA:"},
        {"numero": "DECIMA OCTAVA: ", "titulo": "DOCUMENTOS DE NO VINCULACION", "reemplazo": "DECIMA OCTAVA:"},
        {"numero": "DECIMA NOVENA: ", "titulo": "CUMPLIMIENTO DE LA CONDICION SUSPENSIVA", "reemplazo": "DECIMA NOVENA:"},
        {"numero": "VIGESIMA: ", "titulo": "DISPOSICIONES VARIAS", "reemplazo": "V I G E S I M A:"},
        {"numero": "VIGESIMA PRIMERA: ", "titulo": "LEY APLICABLE, DOMICILIOS", "reemplazo": "VIGESIMA PRIMERA:"}
    ],
    "Buenas Inversiones S.A.C.": [
        {"numero": "CLAUSULA PRIMERA: ", "titulo": "ANTECEDENTES", "reemplazo": "CLAUSULA PRIMERA:"},
        {"numero": "CLAUSULA SEGUNDA: ", "titulo": "BIENES OBJETO DEL CONTRATO", "reemplazo": "CLAUSULA SEGUNDA:"},
        {"numero": "TERCERA: ", "titulo": "PRECIO Y FORMA DE PAGO", "reemplazo": "T E R C E R A:"},
        {"numero": "CUARTA: ", "titulo": "FALTA DE PAGO DEL PRECIO", "reemplazo": "C U A R T A:"},
        {"numero": "QUINTA: ", "titulo": "CONDICION SUSPENSIVA", "reemplazo": "Q U I N T A:"},
        {"numero": "SEXTA: ", "titulo": "FALTA DE ENTREGA OPORTUNA", "reemplazo": "S E X T A:"},
        {"numero": "SETIMA: ", "titulo": "ENTREGA DE LAS UNIDADES INMOBILIARIAS", "reemplazo": "S E T I M A:"},
        {"numero": "OCTAVA: ", "titulo": "OBLIGACIONES DE MET", "reemplazo": "O C T A V A:"},
        {"numero": "NOVENA: ", "titulo": "OBLIGACIONES DE EL COMPRADOR", "reemplazo": "N O V E N A:"},
        {"numero": "DECIMO: ", "titulo": "DECLARACIONES DE LAS PARTES", "reemplazo": "D E C I M O:"},
        {"numero": "DECIMO PRIMERA: ", "titulo": "RESOLUCION DE LA COMPRAVENTA", "reemplazo": "DECIMO PRIMERA:"},
        {"numero": "DECIMO SEGUNDA: ", "titulo": "CARGAS, GRAVAMENES Y FIDEICOMISO", "reemplazo": "DECIMO SEGUNDA:"},
        {"numero": "DECIMO TERCERA: ", "titulo": "GASTOS Y TRIBUTOS", "reemplazo": "DECIMO TERCERA:"},
        {"numero": "DECIMO CUARTA: ", "titulo": "SERVICIOS COMUNES E INDEPENDIENTES", "reemplazo": "DECIMO CUARTA:"},
        {"numero": "DECIMO QUINTA: ", "titulo": "DE LA ADMINISTRACION DEL EDIFICIO", "reemplazo": "DECIMO QUINTA:"},
        {"numero": "DECIMO SEXTA: ", "titulo": "SOLUCION DE CONTROVERSIAS", "reemplazo": "DECIMO SEXTA:"},
        {"numero": "DECIMO SETIMA: ", "titulo": "DOMICILIO", "reemplazo": "DECIMO SETIMA:"},
        {"numero": "DECIMO OCTAVA: ", "titulo": "APLICACION SUPLETORIA DE LA LEY", "reemplazo": "DECIMO OCTAVA:"}
    ],
    "Espinoza Arquitectos S.A.C.": [
        {"numero": "PRIMERA: ", "titulo": "DE LAS DEFINICIONES", "reemplazo": "P R I M E R A:"},
        {"numero": "SEGUNDA: ", "titulo": "DEL OBJETO DEL PRESENTE CONTRATO", "reemplazo": "S E G U N D A:"},
        {"numero": "TERCERA: ", "titulo": "DEL PRECIO Y DE LA FORMA DE PAGO", "reemplazo": "T E R C E R A:"},
        {"numero": "CUARTA: ", "titulo": "DE LA EXISTENCIA DE LOS INMUEBLES", "reemplazo": "C U A R T A:"},
        {"numero": "QUINTA: ", "titulo": "DE LA ENTREGA DE POSESION", "reemplazo": "Q U I N T A:"},
        {"numero": "SEXTA: ", "titulo": "DE LA EQUIVALENCIA DE LAS PRESTACIONES", "reemplazo": "S E X T A:"},
        {"numero": "SETIMA: ", "titulo": "DE LA INEXISTENCIA DE CARGAS", "reemplazo": "S E T I M A:"},
        {"numero": "OCTAVA: ", "titulo": "DE LA RESOLUCION A CARGO DE", "reemplazo": "O C T A V A:"},
        {"numero": "NOVENA: ", "titulo": "DE LA RESOLUCION A CARGO DE", "reemplazo": "N O V E N A:"},
        {"numero": "DECIMA: ", "titulo": "DE LA INEXISTENCIA DE DEUDAS", "reemplazo": "D E C I M A:"},
        {"numero": "DECIMA PRIMERA: ", "titulo": "DE LOS ANEXOS", "reemplazo": "DECIMA PRIMERA:"},
        {"numero": "DECIMA SEGUNDA: ", "titulo": "DE LOS FIDEICOMISOS", "reemplazo": "DECIMA SEGUNDA:"},
        {"numero": "DECIMA TERCERA: ", "titulo": "DE LA INEXISTENCIA DE RESPONSABILIDAD", "reemplazo": "DECIMA TERCERA:"},
        {"numero": "DECIMA CUARTA: ", "titulo": "DEL LAVADO DE ACTIVOS", "reemplazo": "DECIMA CUARTA:"},
        {"numero": "DECIMA QUINTA: ", "titulo": "DE LA ADMINISTRACION", "reemplazo": "DECIMA QUINTA:"},
        {"numero": "DECIMA SEXTA: ", "titulo": "DE LA DECLARACION DE CONOCIMIENTO", "reemplazo": "DECIMA SEXTA:"},
        {"numero": "DECIMA SETIMA: ", "titulo": "DE LAS DISPOSICIONES VARIAS", "reemplazo": "DECIMA SETIMA:"},
        {"numero": "DECIMA OCTAVA: ", "titulo": "CONSTANCIA DE REGISTRO", "reemplazo": "DECIMA OCTAVA:"},
        {"numero": "DECIMA NOVENA: ", "titulo": "CONSTANCIA DE LA GARANTIA", "reemplazo": "DECIMA NOVENA:"},
        {"numero": "VIGESIMA: ", "titulo": "RESPECTO A LA RESPONSABILIDAD", "reemplazo": "V I G E S I M A:"},
        {"numero": "VIGESIMA PRIMERA: ", "titulo": "PODER IRREVOCABLE", "reemplazo": "VIGESIMA PRIMERA:"},
        {"numero": "PRIMERA:", "titulo": "DE LAS DEFINICIONES", "reemplazo": "P R I M E R A:"},
        {"numero": "SEGUNDA:", "titulo": "DEL OBJETO DEL PRESENTE CONTRATO", "reemplazo": "S E G U N D A:"},
        {"numero": "TERCERA:", "titulo": "DEL PRECIO Y DE LA FORMA DE PAGO", "reemplazo": "T E R C E R A:"},
        {"numero": "CUARTA:", "titulo": "DE LA EXISTENCIA DE LOS INMUEBLES", "reemplazo": "C U A R T A:"},
        {"numero": "QUINTA:", "titulo": "DE LA ENTREGA DE POSESION", "reemplazo": "Q U I N T A:"},
        {"numero": "SEXTA:", "titulo": "DE LA EQUIVALENCIA DE LAS PRESTACIONES", "reemplazo": "S E X T A:"},
        {"numero": "SETIMA:", "titulo": "DE LA INEXISTENCIA DE CARGAS", "reemplazo": "S E T I M A:"},
        {"numero": "OCTAVA:", "titulo": "DE LA RESOLUCION A CARGO DE", "reemplazo": "O C T A V A:"},
        {"numero": "NOVENA:", "titulo": "DE LA RESOLUCION A CARGO DE", "reemplazo": "N O V E N A:"},
        {"numero": "DECIMA:", "titulo": "DE LA INEXISTENCIA DE DEUDAS", "reemplazo": "D E C I M A:"},
        {"numero": "DECIMA PRIMERA:", "titulo": "DE LOS ANEXOS", "reemplazo": "DECIMA PRIMERA:"},
        {"numero": "DECIMA SEGUNDA:", "titulo": "DE LOS FIDEICOMISOS", "reemplazo": "DECIMA SEGUNDA:"},
        {"numero": "DECIMA TERCERA:", "titulo": "DE LA INEXISTENCIA DE RESPONSABILIDAD", "reemplazo": "DECIMA TERCERA:"},
        {"numero": "DECIMA CUARTA:", "titulo": "DEL LAVADO DE ACTIVOS", "reemplazo": "DECIMA CUARTA:"},
        {"numero": "DECIMA QUINTA:", "titulo": "DE LA ADMINISTRACION", "reemplazo": "DECIMA QUINTA:"},
        {"numero": "DECIMA SEXTA:", "titulo": "DE LA DECLARACION DE CONOCIMIENTO", "reemplazo": "DECIMA SEXTA:"},
        {"numero": "DECIMA SETIMA:", "titulo": "DE LAS DISPOSICIONES VARIAS", "reemplazo": "DECIMA SETIMA:"},
        {"numero": "DECIMA OCTAVA:", "titulo": "CONSTANCIA DE REGISTRO", "reemplazo": "DECIMA OCTAVA:"},
        {"numero": "DECIMA NOVENA:", "titulo": "CONSTANCIA DE LA GARANTIA", "reemplazo": "DECIMA NOVENA:"},
        {"numero": "VIGESIMA:", "titulo": "RESPECTO A LA RESPONSABILIDAD", "reemplazo": "V I G E S I M A:"},
        {"numero": "VIGESIMA PRIMERA:", "titulo": "PODER IRREVOCABLE", "reemplazo": "VIGESIMA PRIMERA:"}
    ],
    "Josmi Grupo Inversor S.A.C.": [
        {"numero": "CLAUSULA PRIMERA: ", "titulo": "ANTECEDENTES", "reemplazo": "CLAUSULA PRIMERA."},
        {"numero": "CLAUSULA SEGUNDA: ", "titulo": "OBJETO", "reemplazo": "CLAUSULA SEGUNDA."},
        {"numero": "CLAUSULA TERCERA: ", "titulo": "CONTRAPRESTACION", "reemplazo": "CLAUSULA TERCERA."},
        {"numero": "CLAUSULA CUARTA: ", "titulo": "DECLARATORIA DE FABRICA", "reemplazo": "CLAUSULA CUARTA."},
        {"numero": "CLAUSULA QUINTA: ", "titulo": "PLAZO PARA LA ENTREGA", "reemplazo": "CLAUSULA QUINTA."},
        {"numero": "CLAUSULA SEXTA: ", "titulo": "REGLAMENTO INTERNO", "reemplazo": "CLAUSULA SEXTA."},
        {"numero": "CLAUSULA SETIMA: ", "titulo": "OBLIGACIONES DE", "reemplazo": "CLAUSULA SETIMA."},
        {"numero": "CLAUSULA OCTAVA: ", "titulo": "RESOLUCION DEL CONTRATO", "reemplazo": "CLAUSULA OCTAVA."},
        {"numero": "CLAUSULA NOVENA: ", "titulo": "DECLARACIONES DE LAS PARTES", "reemplazo": "CLAUSULA NOVENA."},
        {"numero": "CLAUSULA DECIMA: ", "titulo": "TRAMITES, TRIBUTOS", "reemplazo": "CLAUSULA DECIMA."},
        {"numero": "CLAUSULA DECIMO PRIMERA: ", "titulo": "LEY APLICABLE Y DOMICILIOS", "reemplazo": "CLAUSULA DECIMO PRIMERA."},
        {"numero": "CLAUSULA DECIMO SEGUNDA: ", "titulo": "DISCREPANCIAS Y ARBITRAJE", "reemplazo": "CLAUSULA DECIMO SEGUNDA."},
        {"numero": "CLAUSULA PRIMERA.- ", "titulo": "ANTECEDENTES", "reemplazo": "CLAUSULA PRIMERA."},
        {"numero": "CLAUSULA SEGUNDA.- ", "titulo": "OBJETO", "reemplazo": "CLAUSULA SEGUNDA."},
        {"numero": "CLAUSULA TERCERA.- ", "titulo": "CONTRAPRESTACION", "reemplazo": "CLAUSULA TERCERA."},
        {"numero": "CLAUSULA CUARTA.- ", "titulo": "DECLARATORIA DE FABRICA", "reemplazo": "CLAUSULA CUARTA."},
        {"numero": "CLAUSULA QUINTA.- ", "titulo": "PLAZO PARA LA ENTREGA", "reemplazo": "CLAUSULA QUINTA."},
        {"numero": "CLAUSULA SEXTA.- ", "titulo": "REGLAMENTO INTERNO", "reemplazo": "CLAUSULA SEXTA."},
        {"numero": "CLAUSULA SETIMA.- ", "titulo": "OBLIGACIONES DE", "reemplazo": "CLAUSULA SETIMA."},
        {"numero": "CLAUSULA OCTAVA.- ", "titulo": "RESOLUCION DEL CONTRATO", "reemplazo": "CLAUSULA OCTAVA."},
        {"numero": "CLAUSULA NOVENA.- ", "titulo": "DECLARACIONES DE LAS PARTES", "reemplazo": "CLAUSULA NOVENA."},
        {"numero": "CLAUSULA DECIMA.- ", "titulo": "TRAMITES, TRIBUTOS", "reemplazo": "CLAUSULA DECIMA."},
        {"numero": "CLAUSULA DECIMO PRIMERA.- ", "titulo": "LEY APLICABLE Y DOMICILIOS", "reemplazo": "CLAUSULA DECIMO PRIMERA."},
        {"numero": "CLAUSULA DECIMO SEGUNDA.- ", "titulo": "DISCREPANCIAS Y ARBITRAJE", "reemplazo": "CLAUSULA DECIMO SEGUNDA."}
    ],
    "Paz Centenario S.A.": [
        {"numero": "CLAUSULA PRIMERA: ", "titulo": "ANTECEDENTES", "reemplazo": "CLAUSULA PRIMERA:"},
        {"numero": "CLAUSULA SEGUNDA: ", "titulo": "BIEN (ES) OBJETO", "reemplazo": "CLAUSULA SEGUNDA:"},
        {"numero": "CLAUSULA TERCERA: ", "titulo": "PRECIO DE VENTA", "reemplazo": "CLAUSULA TERCERA:"},
        {"numero": "CLAUSULA CUARTA: ", "titulo": "INCUMPLIMIENTO DE PAGO", "reemplazo": "CLAUSULA CUARTA:"},
        {"numero": "CLAUSULA QUINTA: ", "titulo": "RESOLUCION DEL CONTRATO", "reemplazo": "CLAUSULA QUINTA:"},
        {"numero": "CLAUSULA SEXTA: ", "titulo": "DEFENSA POSESORIA", "reemplazo": "CLAUSULA SEXTA:"},
        {"numero": "CLAUSULA SETIMA: ", "titulo": "RESERVA DE PROPIEDAD", "reemplazo": "CLAUSULA SETIMA:"},
        {"numero": "CLAUSULA OCTAVA: ", "titulo": "ENTREGA DE EL/LOS INMUEBLE", "reemplazo": "CLAUSULA OCTAVA:"},
        {"numero": "CLAUSULA NOVENA: ", "titulo": "EQUIVALENCIA DE LAS PRESTACIONES", "reemplazo": "CLAUSULA NOVENA:"},
        {"numero": "CLAUSULA DECIMA: ", "titulo": "OBLIGACIONES DE LA VENDEDORA", "reemplazo": "CLAUSULA DECIMA:"},
        {"numero": "CLAUSULA UNDECIMA: ", "titulo": "OBLIGACIONES DE EL/LOS", "reemplazo": "CLAUSULA UNDECIMA:"},
        {"numero": "CLAUSULA DUODECIMA: ", "titulo": "INDEPENDIZACION Y TRAMITES MUNICIPALES", "reemplazo": "CLAUSULA DUODECIMA:"},
        {"numero": "CLAUSULA DECIMO TERCERA: ", "titulo": "TRIBUTOS", "reemplazo": "CLAUSULA DECIMO TERCERA:"},
        {"numero": "CLAUSULA DECIMO CUARTA: ", "titulo": "GASTOS DE MANTENIMIENTO", "reemplazo": "CLAUSULA DECIMO CUARTA:"},
        {"numero": "CLAUSULA DECIMO QUINTA: ", "titulo": "DOMICILIOS", "reemplazo": "CLAUSULA DECIMO QUINTA:"},
        {"numero": "CLAUSULA DECIMO SEXTA: ", "titulo": "DECLARACIONES DE", "reemplazo": "CLAUSULA DECIMO SEXTA:"},
        {"numero": "CLAUSULA DECIMO SETIMA: ", "titulo": "INFORMACION SOBRE CONSUMOS", "reemplazo": "CLAUSULA DECIMO SETIMA:"},
        {"numero": "CLAUSULA DECIMO OCTAVA: ", "titulo": "AUTORIZACION DE USO DE DATOS", "reemplazo": "CLAUSULA DECIMO OCTAVA:"},
        {"numero": "CLAUSULA DECIMO NOVENA: ", "titulo": "SOLUCION DE CONFLICTOS", "reemplazo": "CLAUSULA DECIMO NOVENA:"}
    ],
    "Promotora Albamar S.A.C.": [
        {"numero": "PRIMERA.- ", "reemplazo": "P R I M E R A."},
        {"numero": "SEGUNDA.- ", "reemplazo": "S E G U N D A."},
        {"numero": "TERCERA.- ", "reemplazo": "T E R C E R A."},
        {"numero": "CUARTA.- ", "reemplazo": "C U A R T A."},
        {"numero": "QUINTA.- ", "reemplazo": "Q U I N T A."},
        {"numero": "SEXTA.- ", "reemplazo": "S E X T A."},
        {"numero": "SEPTIMA.- ", "reemplazo": "S E P T I M A."},
        {"numero": "OCTAVA.- ", "reemplazo": "O C T A V A."},
        {"numero": "NOVENA.- ", "reemplazo": "N O V E N A."},
        {"numero": "DECIMA.- ", "reemplazo": "D E C I M A."},
        {"numero": "DECIMO PRIMERA.- ", "reemplazo": "DECIMO PRIMERA."},
        {"numero": "DECIMO SEGUNDA.- ", "reemplazo": "DECIMO SEGUNDA."},
        {"numero": "DECIMO TERCERA.- ", "reemplazo": "DECIMO TERCERA."},
        {"numero": "DECIMO CUARTA.- ", "reemplazo": "DECIMO CUARTA."},
        {"numero": "DECIMO QUINTA.- ", "reemplazo": "DECIMO QUINTA."},
        {"numero": "DECIMO SEXTA.- ", "reemplazo": "DECIMO SEXTA."},
        {"numero": "DECIMO SEPTIMA.- ", "reemplazo": "DECIMO SEPTIMA."},
        {"numero": "DECIMO OCTAVA.- ", "reemplazo": "DECIMO OCTAVA."},
        {"numero": "DECIMO NOVENA.- ", "reemplazo": "DECIMO NOVENA."},
        {"numero": "VIGESIMA.- ", "reemplazo": "V I G E S I M A."},
        {"numero": "PRIMERA- ", "reemplazo": "P R I M E R A."},
        {"numero": "SEGUNDA- ", "reemplazo": "S E G U N D A."},
        {"numero": "TERCERA- ", "reemplazo": "T E R C E R A."},
        {"numero": "CUARTA- ", "reemplazo": "C U A R T A."},
        {"numero": "QUINTA- ", "reemplazo": "Q U I N T A."},
        {"numero": "SEXTA- ", "reemplazo": "S E X T A."},
        {"numero": "SEPTIMA- ", "reemplazo": "S E P T I M A."},
        {"numero": "OCTAVA- ", "reemplazo": "O C T A V A."},
        {"numero": "NOVENA- ", "reemplazo": "N O V E N A."},
        {"numero": "DECIMA- ", "reemplazo": "D E C I M A."},
        {"numero": "DECIMO PRIMERA- ", "reemplazo": "DECIMO PRIMERA."},
        {"numero": "DECIMO SEGUNDA- ", "reemplazo": "DECIMO SEGUNDA."},
        {"numero": "DECIMO TERCERA- ", "reemplazo": "DECIMO TERCERA."},
        {"numero": "DECIMO CUARTA- ", "reemplazo": "DECIMO CUARTA."},
        {"numero": "DECIMO QUINTA- ", "reemplazo": "DECIMO QUINTA."},
        {"numero": "DECIMO SEXTA- ", "reemplazo": "DECIMO SEXTA."},
        {"numero": "DECIMO SEPTIMA- ", "reemplazo": "DECIMO SEPTIMA."},
        {"numero": "DECIMO OCTAVA- ", "reemplazo": "DECIMO OCTAVA."},
        {"numero": "DECIMO NOVENA- ", "reemplazo": "DECIMO NOVENA."},
        {"numero": "VIGESIMA- ", "reemplazo": "V I G E S I M A."}
    ],
    "Lider Ingenieria y Contruccion": [
        {"numero": "PRIMERO.- ", "titulo": "ANTECEDENTES", "reemplazo": "P R I M E R O."},
        {"numero": "SEGUNDO.- ", "titulo": "", "reemplazo": "S E G U N D O."},
        {"numero": "TERCERO.- ", "titulo": "OBJETO DEL CONTRATO", "reemplazo": "T E R C E R O."},
        {"numero": "CUARTO.- ", "titulo": "PRECIO Y FORMA DE PAGO", "reemplazo": "C U A R T O."},
        {"numero": "QUINTO.- ", "titulo": "OBLIGACIONES DE LAS PARTES", "reemplazo": "Q U I N T O."},
        {"numero": "SEXTO.- ", "titulo": "INSCRIPCION DE LA DECLARATORIA DE FABRICA", "reemplazo": "S E X T O."},
        {"numero": "SETIMO.- ", "titulo": "CONSTITUCION Y LEVANTAMIENTO", "reemplazo": "S E T I M O."},
        {"numero": "OCTAVO.- ", "titulo": "SOMETIMIENTO AL REGLAMENTO", "reemplazo": "O C T A V O."},
        {"numero": "NOVENO.- ", "titulo": "DE LA RESOLUCION", "reemplazo": "N O V E N O."},
        {"numero": "DECIMO.- ", "titulo": "SERVICIO POST-VENTA", "reemplazo": "D E C I M O."},
        {"numero": "DECIMO PRIMERO.- ", "titulo": "GASTOS Y TRIBUTOS", "reemplazo": "DECIMO PRIMERO."},
        {"numero": "DECIMO SEGUNDO.- ", "titulo": "OTORGAMIENTO DE PODER", "reemplazo": "DECIMO SEGUNDO."},
        {"numero": "DECIMO TERCERO.- ", "titulo": "CONSTATACION DE LA EXISTENCIA", "reemplazo": "DECIMO TERCERO."},
        {"numero": "DECIMO CUARTO.- ", "titulo": "EQUIVALENCIA DE PRESTACIONES", "reemplazo": "DECIMO CUARTO."},
        {"numero": "DECIMO QUINTO.- ", "titulo": "RESOLUCION DE CONTROVERSIAS", "reemplazo": "DECIMO QUINTO."},
        {"numero": "DECIMO SEXTO.- ", "titulo": "DOMICILIO", "reemplazo": "DECIMO SEXTO."},
        {"numero": "DECIMO SETIMO.- ", "titulo": "VARIOS", "reemplazo": "DECIMO SETIMO."},
        {"numero": "DECIMO OCTAVO.- ", "titulo": "CERTIFICACION DE PROYECTO", "reemplazo": "DECIMO OCTAVO."}
    ],
    "Inversiones Inmobiliarias del Indico": [
        {"numero": "PRIMERA : ", "titulo": "ANTECEDENTES", "reemplazo": "P R I M E R A:"},
        {"numero": "SEGUNDA : ", "titulo": "BIENES OBJETO DEL CONTRATO", "reemplazo": "S E G U N D A:"},
        {"numero": "TERCERA : ", "titulo": "OBJETO DEL PRESENTE CONTRATO", "reemplazo": "T E R C E R A:"},
        {"numero": "CUARTA : ", "titulo": "CONDICION SUSPENSIVA", "reemplazo": "C U A R T A:"},
        {"numero": "QUINTA : ", "titulo": "RESERVA DE PROPIEDAD", "reemplazo": "Q U I N T A:"},
        {"numero": "SEXTA : ", "titulo": "PRECIO Y FORMA DE PAGO", "reemplazo": "S E X T A:"},
        {"numero": "SETIMA : ", "titulo": "FALTA DE PAGO", "reemplazo": "S E T I M A:"},
        {"numero": "OCTAVA : ", "titulo": "ENTREGA DE LOS INMUEBLES", "reemplazo": "O C T A V A:"},
        {"numero": "NOVENA : ", "titulo": "EQUIVALENCIA DE LAS PRESTACIONES", "reemplazo": "N O V E N A:"},
        {"numero": "DECIMA : ", "titulo": "SITUACION DEL PROYECTO", "reemplazo": "D E C I M A:"},
        {"numero": "DECIMO PRIMERA : ", "titulo": "INDEPENDIZACION", "reemplazo": "DECIMO PRIMERA:"},
        {"numero": "DECIMO SEGUNDA : ", "titulo": "IMPUESTOS Y ARBITRIOS", "reemplazo": "DECIMO SEGUNDA:"},
        {"numero": "DECIMO TERCERA : ", "titulo": "DE LA ADMINISTRACION DEL CONJUNTO", "reemplazo": "DECIMO TERCERA:"},
        {"numero": "DECIMO CUARTA : ", "titulo": "GASTOS DE MANTENIMIENTO", "reemplazo": "DECIMO CUARTA:"},
        {"numero": "DECIMO QUINTA : ", "titulo": "FORMALIZACION", "reemplazo": "DECIMO QUINTA:"},
        {"numero": "DECIMO SEXTA : ", "titulo": "DE LA GARANTIA", "reemplazo": "DECIMO SEXTA:"},
        {"numero": "DECIMO SETIMA : ", "titulo": "ACUERDO GLOBAL", "reemplazo": "DECIMO SETIMA:"},
        {"numero": "DECIMO OCTAVA : ", "titulo": "NOTIFICACIONES", "reemplazo": "DECIMO OCTAVA:"},
        {"numero": "DECIMO NOVENA : ", "titulo": "PROTECCION DE DATOS", "reemplazo": "DECIMO NOVENA:"},
        {"numero": "PRIMERA: ", "titulo": "ANTECEDENTES", "reemplazo": "P R I M E R A:"},
        {"numero": "SEGUNDA: ", "titulo": "BIENES OBJETO DEL CONTRATO", "reemplazo": "S E G U N D A:"},
        {"numero": "TERCERA: ", "titulo": "OBJETO DEL PRESENTE CONTRATO", "reemplazo": "T E R C E R A:"},
        {"numero": "CUARTA: ", "titulo": "CONDICION SUSPENSIVA", "reemplazo": "C U A R T A:"},
        {"numero": "QUINTA: ", "titulo": "RESERVA DE PROPIEDAD", "reemplazo": "Q U I N T A:"},
        {"numero": "SEXTA: ", "titulo": "PRECIO Y FORMA DE PAGO", "reemplazo": "S E X T A:"},
        {"numero": "SETIMA: ", "titulo": "FALTA DE PAGO", "reemplazo": "S E T I M A:"},
        {"numero": "OCTAVA: ", "titulo": "ENTREGA DE LOS INMUEBLES", "reemplazo": "O C T A V A:"},
        {"numero": "NOVENA: ", "titulo": "EQUIVALENCIA DE LAS PRESTACIONES", "reemplazo": "N O V E N A:"},
        {"numero": "DECIMA: ", "titulo": "SITUACION DEL PROYECTO", "reemplazo": "D E C I M A:"},
        {"numero": "DECIMO PRIMERA: ", "titulo": "INDEPENDIZACION", "reemplazo": "DECIMO PRIMERA:"},
        {"numero": "DECIMO SEGUNDA: ", "titulo": "IMPUESTOS Y ARBITRIOS", "reemplazo": "DECIMO SEGUNDA:"},
        {"numero": "DECIMO TERCERA: ", "titulo": "DE LA ADMINISTRACION DEL CONJUNTO", "reemplazo": "DECIMO TERCERA:"},
        {"numero": "DECIMO CUARTA: ", "titulo": "GASTOS DE MANTENIMIENTO", "reemplazo": "DECIMO CUARTA:"},
        {"numero": "DECIMO QUINTA: ", "titulo": "FORMALIZACION", "reemplazo": "DECIMO QUINTA:"},
        {"numero": "DECIMO SEXTA: ", "titulo": "DE LA GARANTIA", "reemplazo": "DECIMO SEXTA:"},
        {"numero": "DECIMO SETIMA: ", "titulo": "ACUERDO GLOBAL", "reemplazo": "DECIMO SETIMA:"},
        {"numero": "DECIMO OCTAVA: ", "titulo": "NOTIFICACIONES", "reemplazo": "DECIMO OCTAVA:"},
        {"numero": "DECIMO NOVENA: ", "titulo": "PROTECCION DE DATOS", "reemplazo": "DECIMO NOVENA:"}
    ],
    "general": [
        {"numero": "PRIMERA", "reemplazo": "P R I M E R A:"},
        {"numero": "SEGUNDA", "reemplazo": "S E G U N D A:"},
        {"numero": "TERCERA", "reemplazo": "T E R C E R A:"},
        {"numero": "CUARTA", "reemplazo": "C U A R T A:"},
        {"numero": "QUINTA", "reemplazo": "Q U I N T A:"},
        {"numero": "SEXTA", "reemplazo": "S E X T A:"},
        {"numero": "SETIMA", "reemplazo": "S E T I M A:"},
        {"numero": "SEPTIMA", "reemplazo": "S E P T I M A:"},
        {"numero": "OCTAVA", "reemplazo": "O C T A V A:"},
        {"numero": "NOVENA", "reemplazo": "N O V E N A:"},
        {"numero": "DECIMA", "reemplazo": "D E C I M A:"},
        {"numero": "DECIMA PRIMERA", "reemplazo": "DECIMA PRIMERA:"},
        {"numero": "DECIMA SEGUNDA", "reemplazo": "DECIMA SEGUNDA:"},
        {"numero": "DECIMA TERCERA", "reemplazo": "DECIMA TERCERA:"},
        {"numero": "DECIMA CUARTA", "reemplazo": "DECIMA CUARTA:"},
        {"numero": "DECIMA QUINTA", "reemplazo": "DECIMA QUINTA:"},
        {"numero": "DECIMA SEXTA", "reemplazo": "DECIMA SEXTA:"},
        {"numero": "DECIMA SEPTIMA", "reemplazo": "DECIMA SEPTIMA:"},
        {"numero": "DECIMA OCTAVA", "reemplazo": "DECIMA OCTAVA:"},
        {"numero": "DECIMA NOVENA", "reemplazo": "DECIMA NOVENA:"},
        {"numero": "VIGESIMA", "reemplazo": "V I G E S I M A:"},
        {"numero": "VIGESIMA PRIMERA", "reemplazo": "VIGESIMA PRIMERA:"},
        {"numero": "VIGESIMA SEGUNDA", "reemplazo": "VIGESIMA SEGUNDA:"},
        {"numero": "VIGESIMA TERCERA", "reemplazo": "VIGESIMA TERCERA:"},
        {"numero": "VIGESIMA CUARTA", "reemplazo": "VIGESIMA CUARTA:"},
        {"numero": "VIGESIMA QUINTA", "reemplazo": "VIGESIMA QUINTA:"},
        {"numero": "VIGESIMA SEXTA", "reemplazo": "VIGESIMA SEXTA:"},
        {"numero": "VIGESIMA SEPTIMA", "reemplazo": "VIGESIMA SEPTIMA:"},
        {"numero": "VIGESIMA OCTAVA", "reemplazo": "VIGESIMA OCTAVA:"},
        {"numero": "VIGESIMA NOVENA", "reemplazo": "VIGESIMA NOVENA:"},
        {"numero": "PRIMERO", "reemplazo": "P R I M E R O:"},
        {"numero": "SEGUNDO", "reemplazo": "S E G U N D O:"},
        {"numero": "TERCERO", "reemplazo": "T E R C E R O:"},
        {"numero": "CUARTO", "reemplazo": "C U A R T O:"},
        {"numero": "QUINTO", "reemplazo": "Q U I N T O:"},
        {"numero": "SEXTO", "reemplazo": "S E X T O:"},
        {"numero": "SETIMO", "reemplazo": "S E T I M O:"},
        {"numero": "OCTAVO", "reemplazo": "O C T A V O:"},
        {"numero": "NOVENO", "reemplazo": "N O V E N O:"},
        {"numero": "DECIMO", "reemplazo": "D E C I M O:"},
        {"numero": "DECIMO PRIMERA", "reemplazo": "DECIMO PRIMERA:"},
        {"numero": "DECIMO SEGUNDA", "reemplazo": "DECIMO SEGUNDA:"},
        {"numero": "DECIMO TERCERA", "reemplazo": "DECIMO TERCERA:"},
        {"numero": "DECIMO CUARTA", "reemplazo": "DECIMO CUARTA:"},
        {"numero": "DECIMO QUINTA", "reemplazo": "DECIMO QUINTA:"},
        {"numero": "DECIMO SEXTA", "reemplazo": "DECIMO SEXTA:"},
        {"numero": "DECIMO SEPTIMA", "reemplazo": "DECIMO SEPTIMA:"},
        {"numero": "DECIMO OCTAVA", "reemplazo": "DECIMO OCTAVA:"},
        {"numero": "DECIMO NOVENA", "reemplazo": "DECIMO NOVENA:"},
        {"numero": "DECIMOPRIMERA", "reemplazo": "DECIMOPRIMERA:"},
        {"numero": "DECIMOSEGUNDA", "reemplazo": "DECIMOSEGUNDA:"},
        {"numero": "DECIMOTERCERA", "reemplazo": "DECIMOTERCERA:"},
        {"numero": "DECIMOCUARTA", "reemplazo": "DECIMOCUARTA:"},
        {"numero": "DECIMOQUINTA", "reemplazo": "DECIMOQUINTA:"},
        {"numero": "DECIMOSEXTA", "reemplazo": "DECIMOSEXTA:"},
        {"numero": "DECIMOSEPTIMA", "reemplazo": "DECIMOSEPTIMA:"},
        {"numero": "DECIMOOCTAVA", "reemplazo": "DECIMOOCTAVA:"},
        {"numero": "DECIMONOVENA", "reemplazo": "DECIMONOVENA:"},
        {"numero": "VIGESIMO", "reemplazo": "V I G E S I M O:"},
        {"numero": "VIGESIMO PRIMERA", "reemplazo": "VIGESIMO PRIMERA:"},
        {"numero": "VIGESIMO SEGUNDA", "reemplazo": "VIGESIMO SEGUNDA:"},
        {"numero": "VIGESIMO TERCERA", "reemplazo": "VIGESIMO TERCERA:"},
        {"numero": "VIGESIMO CUARTA", "reemplazo": "VIGESIMO CUARTA:"},
        {"numero": "VIGESIMO QUINTA", "reemplazo": "VIGESIMO QUINTA:"},
        {"numero": "VIGESIMO SEXTA", "reemplazo": "VIGESIMO SEXTA:"},
        {"numero": "VIGESIMO SEPTIMA", "reemplazo": "VIGESIMO SEPTIMA:"},
        {"numero": "VIGESIMO OCTAVA", "reemplazo": "VIGESIMO OCTAVA:"},
        {"numero": "VIGESIMO NOVENA", "reemplazo": "VIGESIMO NOVENA:"}
    ]
}